bolinette/web/README.md
bolinette/web/__init__.py
bolinette/web/abstract/__init__.py
bolinette/web/abstract/request.py
bolinette/web/abstract/response.py
bolinette/web/asgi/__init__.py
bolinette/web/asgi/app.py
bolinette/web/asgi/requests.py
bolinette/web/asgi/responses.py
bolinette/web/asgi/types.py
bolinette/web/config.py
bolinette/web/controller.py
bolinette/web/exceptions.py
bolinette/web/extension.py
bolinette/web/middleware.py
bolinette/web/payload.py
bolinette/web/py.typed
bolinette/web/pyproject.toml
bolinette/web/resources/__init__.py
bolinette/web/resources/data.py
bolinette/web/resources/headers.py
bolinette/web/resources/resolvers.py
bolinette/web/resources/resources.py
bolinette/web/resources/writer.py
bolinette/web/routing/__init__.py
bolinette/web/routing/decorators.py
bolinette/web/routing/resource.py
bolinette/web/routing/router.py
bolinette/web/ws/__init__.py
bolinette/web/ws/channel.py
bolinette/web/ws/handler.py
bolinette/web/ws/requests.py
bolinette/web/ws/sub.py
bolinette/web/ws/topic.py
bolinette_web-0.18.2.dist-info/LICENSE.txt
bolinette_web-0.18.2.dist-info/METADATA
bolinette_web-0.18.2.dist-info/WHEEL
bolinette_web-0.18.2.dist-info/RECORD
