Metadata-Version: 2.1
Name: bolinette-web
Version: 0.18.2
Summary: The Bolinette web package, an async Http and Websocket framework, based on Bolinette
Home-page: https://bolinette.org
License: MIT
Keywords: Bolinette,Framework,Http,Websocket
Author: Pierre Chat
Author-email: pierrechat@outlook.com
Requires-Python: >=3.12,<4.0
Classifier: Development Status :: 4 - Beta
Classifier: Intended Audience :: Developers
Classifier: License :: OSI Approved :: MIT License
Classifier: Programming Language :: Python :: 3
Classifier: Programming Language :: Python :: 3.12
Classifier: Topic :: Software Development :: Build Tools
Requires-Dist: bolinette (>=0.18.2,<0.19.0)
Project-URL: Documentation, https://bolinette.org/docs
Project-URL: Repository, https://github.com/bolinette/bolinette
